django_sourcerer/__init__.py
django_sourcerer/apps.py
django_sourcerer/asgi.py
django_sourcerer/models.py
django_sourcerer/serializers.py
django_sourcerer/settings.py
django_sourcerer/urls.py
django_sourcerer/views.py
django_sourcerer/wsgi.py
django_sourcerer/import_datas/__init__.py
django_sourcerer/import_datas/csvHandler.py
django_sourcerer/import_datas/importer.py
django_sourcerer/import_datas/intermediate_layer.py
django_sourcerer/import_datas/jsonHandler.py
django_sourcerer/import_datas/parsing_config_file.py
django_sourcerer/management/__init__.py
django_sourcerer/management/commands/__init__.py
django_sourcerer/management/commands/update_objects.py
tests/__init__.py
tests/test_import_csv_data.py
tests/test_intermediate_layer.py
django_sourcerer-2.1.dist-info/LICENSE
django_sourcerer-2.1.dist-info/METADATA
django_sourcerer-2.1.dist-info/WHEEL
django_sourcerer-2.1.dist-info/top_level.txt
django_sourcerer-2.1.dist-info/RECORD
