Metadata-Version: 2.1
Name: django-sourcerer
Version: 2.1
Summary: Django app that import and correlating data from external sources.
Home-page: https://github.com/nokia-wroclaw/innovativeproject-django-sourcerer
Author: Cem Arslan, Kadir Kocak, Ugur Dogus Hamarat, Cagatay Em, Farid Murmadov, Burak Karaca
Author-email: cmarslan06@gmail.com
License: UNKNOWN
Platform: UNKNOWN
Classifier: Programming Language :: Python :: 3
Classifier: License :: OSI Approved :: MIT License
Classifier: Operating System :: OS Independent
Requires-Python: >=3.6
Requires-Dist: django (==3.0.5)
Requires-Dist: djangorestframework (==3.11.0)
Requires-Dist: requests (==2.23.0)
Requires-Dist: pyyaml (==5.3.1)
Requires-Dist: pandas (==1.0.3)
Requires-Dist: pytest (==5.4.1)
Requires-Dist: requests-mock (==1.7.0)
